README.rst
setup.py
benchit/__init__.py
benchit/main.py
benchit/utils.py
benchit.egg-info/PKG-INFO
benchit.egg-info/SOURCES.txt
benchit.egg-info/dependency_links.txt
benchit.egg-info/not-zip-safe
benchit.egg-info/requires.txt
benchit.egg-info/top_level.txt