Metadata-Version: 2.1
Name: benchit
Version: 0.0.5
Summary: Benchmarking tools for Python
Home-page: https://github.com/droyed/benchit
Author: Divakar Roy
Author-email: droygatech@gmail.com
License: MIT
Keywords: benchmarking performance timing timeit
Platform: any
Classifier: Development Status :: 3 - Alpha
Classifier: Intended Audience :: Developers
Classifier: Topic :: System :: Benchmark
Classifier: License :: OSI Approved :: MIT License
Classifier: Programming Language :: Python :: 2.7
Classifier: Programming Language :: Python :: 3.5
Classifier: Programming Language :: Python :: 3.6
Classifier: Programming Language :: Python :: 3.7
Classifier: Programming Language :: Python :: 3.8
Classifier: Operating System :: OS Independent
Provides-Extra: development
Provides-Extra: maintainer
Provides-Extra: test
Provides-Extra: optional
